committer-0.2.0.data/scripts/ci
committer-0.2.0.data/scripts/up
committer-0.2.0.data/scripts/st
committer/LICENSE.txt
committer/errors.py
committer/__init__.py
committer/actions.py
committer/execution.py
committer/vcsclients/__init__.py
committer/vcsclients/detection.py
committer/vcsclients/mercurial.py
committer/vcsclients/git.py
committer/vcsclients/subversion.py
committer-0.2.0.dist-info/pydist.json
committer-0.2.0.dist-info/top_level.txt
committer-0.2.0.dist-info/zip-safe
committer-0.2.0.dist-info/RECORD
committer-0.2.0.dist-info/METADATA
committer-0.2.0.dist-info/WHEEL
committer-0.2.0.dist-info/DESCRIPTION.rst
