Metadata-Version: 2.0
Name: committer
Version: 0.2.0
Summary: Unified command line interface for git, mercurial and subversion.
Home-page: https://github.com/aelgru/committer
Author: Michael Gruber
Author-email: aelgru@gmail.com
License: Apache License, Version 2.0
Platform: UNKNOWN
Classifier: Development Status :: 4 - Beta
Classifier: Environment :: Console
Classifier: Intended Audience :: Developers
Classifier: License :: OSI Approved :: Apache Software License
Classifier: Programming Language :: Python
Classifier: Topic :: Software Development :: User Interfaces
Classifier: Topic :: Software Development :: Version Control
Classifier: Topic :: Utilities
